_walker.cp39-win_amd64.pyd
walker/__init__.py
walker/preprocessing.py
graph_walker-1.0.4.dist-info/METADATA
graph_walker-1.0.4.dist-info/WHEEL
graph_walker-1.0.4.dist-info/top_level.txt
graph_walker-1.0.4.dist-info/RECORD
