Metadata-Version: 2.1
Name: graph-walker
Version: 1.0.4
Summary: Fastest library for random walks on graph
Home-page: https://github.com/kerighan/graph-walker
Author: Maixent Chenebaux
Author-email: max.chbx@gmail.com
License: UNKNOWN
Platform: UNKNOWN
Classifier: License :: OSI Approved :: MIT License
Classifier: Operating System :: OS Independent
Requires-Dist: networkx
Requires-Dist: numpy
Requires-Dist: scipy
Requires-Dist: pybind11
Requires-Dist: scikit-learn
